[
  {
    "objectId": 5265,
    "globalId": "{0FC6C8D2-75CD-4122-8A5A-75E0E52528D6}",
    "relGlobalId": "{6C857EDB-C46B-4F86-8D8C-80E476214AF4}",
    "createdUser": "Esri_Anonymous",
    "createdDate": 1643760826000,
    "lastEditedUser": "Esri_Anonymous",
    "lastEditedDate": 1643760826000,
    "parentTableName": "unit_info",
    "parentUniqueId": "U_1705997574106",
    "documentType": "Panchnama Form",
    "documentCategory": "Panchnama Form",
    "documentRemarks": "Panchnama Signed"
  }
]
