[
  {
    "objectId": 467,
    "relGlobalId": "{95EDF48A-D488-4C91-B88E-5703F352ABFE}",
    "globalId": "{08DA081F-05D4-42AE-94ED-09BCBB9716D3}",
    "memberId": "M_1705638572636",
    "memberName": "Jaid",
    "memberSpouseName": "zeba",
    "memberContactNo": "7979797979",
    "memberDob": "2020-06-18 12:06:01",
    "memberAge": 34,
    "memberGender": "Male",
    "stayingSinceYear": 2022,
    "maritalStatus": "Married",
    "relationshipWithHoh": "Child",
    "aadharNo": "546464646468",
    "panNo": "FFHPS8598C",
    "rationCardColour": "Central railway",
    "religion": "Judaism",
    "fromState": "Goa",
    "motherTongue": "Marathi",
    "education": "Kindergarten",
    "occupation": "Lawyer",
    "placeOfWork": "Inside Dharavi",
    "typeOfWork": "Information Technology",
    "monthlyIncome": "2008",
    "modeOfTransport": "Central railway",
    "schoolCollegeNameLocation": "hxhshdhd",
    "handicapOrCriticalDisease": "No",
    "stayingWith": "Family",
    "vehicleOwnedDrivenType": "3 wheeler",
    "createdUser": "Esri_Anonymous",
    "createdDate": "2024-01-19 04:30:06",
    "lastEditedUser": "SDE",
    "lastEditedDate": "2024-01-19 06:36:41"
  }
]